brainpy/__init__.py
brainpy/_errors.py
brainpy/channels.py
brainpy/check.py
brainpy/checkpoints.py
brainpy/context.py
brainpy/delay.py
brainpy/deprecations.py
brainpy/dynsys.py
brainpy/helpers.py
brainpy/layers.py
brainpy/measure.py
brainpy/mixin.py
brainpy/neurons.py
brainpy/rates.py
brainpy/runners.py
brainpy/synapses.py
brainpy/synouts.py
brainpy/synplast.py
brainpy/transform.py
brainpy/types.py
brainpy/visualization.py
brainpy/algorithms/__init__.py
brainpy/algorithms/offline.py
brainpy/algorithms/online.py
brainpy/algorithms/utils.py
brainpy/analysis/__init__.py
brainpy/analysis/base.py
brainpy/analysis/constants.py
brainpy/analysis/plotstyle.py
brainpy/analysis/stability.py
brainpy/analysis/highdim/__init__.py
brainpy/analysis/highdim/slow_points.py
brainpy/analysis/highdim/tests/test_slow_points.py
brainpy/analysis/lowdim/__init__.py
brainpy/analysis/lowdim/lowdim_analyzer.py
brainpy/analysis/lowdim/lowdim_bifurcation.py
brainpy/analysis/lowdim/lowdim_phase_plane.py
brainpy/analysis/lowdim/tests/test_bifurcation.py
brainpy/analysis/lowdim/tests/test_phase_plane.py
brainpy/analysis/tests/test_stability.py
brainpy/analysis/utils/__init__.py
brainpy/analysis/utils/function.py
brainpy/analysis/utils/measurement.py
brainpy/analysis/utils/model.py
brainpy/analysis/utils/optimization.py
brainpy/analysis/utils/others.py
brainpy/analysis/utils/outputs.py
brainpy/analysis/utils/visualization.py
brainpy/connect/__init__.py
brainpy/connect/base.py
brainpy/connect/custom_conn.py
brainpy/connect/random_conn.py
brainpy/connect/regular_conn.py
brainpy/connect/tests/test_custom_conn.py
brainpy/connect/tests/test_optimized_result.py
brainpy/connect/tests/test_random_conn.py
brainpy/connect/tests/test_random_conn_visualize.py
brainpy/connect/tests/test_regular_conn.py
brainpy/dnn/__init__.py
brainpy/dnn/activations.py
brainpy/dnn/base.py
brainpy/dnn/conv.py
brainpy/dnn/dropout.py
brainpy/dnn/function.py
brainpy/dnn/interoperation_flax.py
brainpy/dnn/linear.py
brainpy-3.0.1.dist-info/licenses/LICENSE
brainpy-3.0.1.dist-info/METADATA
brainpy-3.0.1.dist-info/WHEEL
brainpy-3.0.1.dist-info/top_level.txt
brainpy-3.0.1.dist-info/RECORD
