Metadata-Version: 2.4
Name: brainpy
Version: 3.0.1
Summary: BrainPy: Brain Dynamics Programming in Python
Author-email: BrainPy Team <chao.brain@qq.com>
License: GPL-3.0 license
Project-URL: Bug Tracker, https://github.com/brainpy/BrainPy/issues
Project-URL: Documentation, https://brainpy.readthedocs.io/
Project-URL: Source Code, https://github.com/brainpy/BrainPy
Keywords: computational neuroscience,brain-inspired computation,brain modeling,brain dynamics modeling,brain dynamics programming
Classifier: Natural Language :: English
Classifier: Operating System :: OS Independent
Classifier: Programming Language :: Python
Classifier: Programming Language :: Python :: 3
Classifier: Programming Language :: Python :: 3.10
Classifier: Programming Language :: Python :: 3.11
Classifier: Programming Language :: Python :: 3.12
Classifier: Programming Language :: Python :: 3.13
Classifier: Intended Audience :: Science/Research
Classifier: License :: OSI Approved :: Apache Software License
Classifier: Topic :: Scientific/Engineering :: Bio-Informatics
Classifier: Topic :: Scientific/Engineering :: Mathematics
Classifier: Topic :: Scientific/Engineering :: Artificial Intelligence
Classifier: Topic :: Software Development :: Libraries
Requires-Python: >=3.10
License-File: LICENSE
Requires-Dist: numpy>=1.15
Requires-Dist: jax
Requires-Dist: tqdm
Requires-Dist: brainstate>=0.2.0
Requires-Dist: brainunit
Requires-Dist: brainevent>=0.0.4
Requires-Dist: braintools>=0.0.9
Provides-Extra: cpu
Requires-Dist: jax[cpu]; extra == "cpu"
Requires-Dist: brainstate; extra == "cpu"
Requires-Dist: brainunit; extra == "cpu"
Requires-Dist: brainevent; extra == "cpu"
Requires-Dist: braintools; extra == "cpu"
Provides-Extra: cuda12
Requires-Dist: jax[cuda12]; extra == "cuda12"
Requires-Dist: brainstate; extra == "cuda12"
Requires-Dist: brainunit; extra == "cuda12"
Requires-Dist: brainevent; extra == "cuda12"
Requires-Dist: braintools; extra == "cuda12"
Provides-Extra: cuda13
Requires-Dist: jax[cuda13]; extra == "cuda13"
Requires-Dist: brainstate; extra == "cuda13"
Requires-Dist: brainunit; extra == "cuda13"
Requires-Dist: brainevent; extra == "cuda13"
Requires-Dist: braintools; extra == "cuda13"
Provides-Extra: tpu
Requires-Dist: jax[tpu]; extra == "tpu"
Requires-Dist: brainstate; extra == "tpu"
Requires-Dist: brainunit; extra == "tpu"
Requires-Dist: brainevent; extra == "tpu"
Requires-Dist: braintools; extra == "tpu"
Dynamic: license-file
